{
  "2026-07-02 09:00": {
    "intl_spot": {
      "name": "国际黄金现货",
      "intl_price": 4050.98,
      "intl_unit": "美元/盎司",
      "cny_price": 884.6483,
      "update_time": "2026-07-01 20:00:00",
      "prev_close": 4031.29
    },
    "au9999": {
      "name": "AU9999",
      "price": 905.75,
      "prev_close": null,
      "change": null,
      "change_rate": null
    },
    "boshi_etf": {
      "name": "博时黄金ETF",
      "code": "159937",
      "price": 8.397,
      "prev_close": 8.255,
      "change": 0.14199999999999946,
      "change_rate": 1.7201695941853354
    },
    "gold_funds": {
      "002610": {
        "name": "博时黄金",
        "code": "002610",
        "etf_name": "博时黄金ETF",
        "etf_price": 8.397,
        "gold_price": 839.7,
        "prev_etf_price": 8.255,
        "prev_gold_price": 825.5,
        "change": 0.14199999999999946,
        "change_rate": 1.7201695941853354
      },
      "000216": {
        "name": "华安黄金",
        "code": "000216",
        "etf_name": "华安黄金ETF",
        "etf_price": 8.418,
        "gold_price": 841.8,
        "prev_etf_price": 8.271,
        "prev_gold_price": 827.1,
        "change": 0.14699999999999847,
        "change_rate": 1.7772941603191688
      },
      "002963": {
        "name": "易方达黄金",
        "code": "002963",
        "etf_name": "易方达黄金ETF",
        "etf_price": 8.792,
        "gold_price": 879.2,
        "prev_etf_price": 8.642,
        "prev_gold_price": 864.2,
        "change": 0.15000000000000036,
        "change_rate": 1.7357093265447856
      },
      "000218": {
        "name": "国泰黄金",
        "code": "000218",
        "etf_name": "国泰黄金ETF",
        "etf_price": 8.823,
        "gold_price": 882.3,
        "prev_etf_price": 8.67,
        "prev_gold_price": 867.0,
        "change": 0.15300000000000047,
        "change_rate": 1.7647058823529467
      },
      "000929": {
        "name": "博时黄金D",
        "code": "000929",
        "etf_name": "博时黄金ETF",
        "etf_price": 8.397,
        "gold_price": 839.7,
        "prev_etf_price": 8.255,
        "prev_gold_price": 825.5,
        "change": 0.14199999999999946,
        "change_rate": 1.7201695941853354
      }
    },
    "brands": {
      "": 1208.0,
      "周六福": 1203.0,
      "老庙黄金": 1208.0,
      "老凤祥": 1208.0,
      "中国黄金": 1188.0,
      "潮宏基": 1208.0,
      "金至尊": 1208.0,
      "谢瑞麟": 1208.0,
      "六福珠宝": 1206.0,
      "周生生": 1213.0,
      "周大福": 1208.0
    }
  }
}